setup.py
src/thirdlight.py
src/thirdlight.egg-info/PKG-INFO
src/thirdlight.egg-info/SOURCES.txt
src/thirdlight.egg-info/dependency_links.txt
src/thirdlight.egg-info/requires.txt
src/thirdlight.egg-info/top_level.txt