Metadata-Version: 1.1
Name: thirdlight
Version: 0.1.0
Summary: Python API library for the ThirdLight image management system
Home-page: https://github.com/Rethought/thirdlight.git
Author: ReThought Ltd
Author-email: code@rethought-solutions.com
License: BSD
Keywords: imaging,asset_management,thirdlight,api
Platform: UNKNOWN
Classifier: Intended Audience :: Developers
Classifier: License :: OSI Approved :: BSD License
Classifier: Operating System :: OS Independent
Classifier: Programming Language :: Python
